covidmx/__init__.py
covidmx/covidmx.py
covidmx/dge.py
covidmx/dge_plot.py
covidmx/serendipia.py
covidmx/utils.py
covidmx/tests/__init__.py
covidmx/tests/test_dge.py
covidmx/tests/test_plots.py
covidmx/tests/test_serendipia.py
covidmx-0.3.1.dist-info/LICENSE
covidmx-0.3.1.dist-info/METADATA
covidmx-0.3.1.dist-info/WHEEL
covidmx-0.3.1.dist-info/top_level.txt
covidmx-0.3.1.dist-info/RECORD
