Metadata-Version: 2.1
Name: covidmx
Version: 0.3.1
Summary: Python API to get information about COVID-19 in México.
Home-page: https://github.com/FedericoGarza/covidmx
Author: Federico Garza
Author-email: fede.garza.ramirez@gmail.com
License: UNKNOWN
Platform: UNKNOWN
Classifier: Programming Language :: Python :: 3
Classifier: License :: OSI Approved :: MIT License
Classifier: Operating System :: OS Independent
Requires-Python: >=3.5
Requires-Dist: more-itertools (>=6.0.0)
Requires-Dist: pandas (>=0.25.2)
Requires-Dist: Unidecode (>=1.1.1)
Requires-Dist: requests (>=2.21.0)
Requires-Dist: xlrd (>=1.2.0)
Requires-Dist: mapsmx (>=0.0.3)
Requires-Dist: matplotlib (>=3.0.3)
Requires-Dist: mapclassify (>=2.2.0)
Requires-Dist: descartes (>=1.1.0)
